maintenancemode/__init__.py
maintenancemode/conf.py
maintenancemode/http.py
maintenancemode/middleware.py
maintenancemode/models.py
maintenancemode/utils.py
maintenancemode/views.py
maintenancemode/management/__init__.py
maintenancemode/management/commands/__init__.py
maintenancemode/management/commands/maintenance.py
maintenancemode/tests/__init__.py
maintenancemode/tests/conftest.py
maintenancemode/tests/models.py
maintenancemode/tests/settings.py
maintenancemode/tests/test_middleware.py
maintenancemode/tests/urls.py
maintenancemode/tests/templates/503.html
django_maintenancemode-0.11.7.dist-info/AUTHORS
django_maintenancemode-0.11.7.dist-info/LICENSE
django_maintenancemode-0.11.7.dist-info/METADATA
django_maintenancemode-0.11.7.dist-info/WHEEL
django_maintenancemode-0.11.7.dist-info/top_level.txt
django_maintenancemode-0.11.7.dist-info/RECORD
