Metadata-Version: 2.1
Name: django-maintenancemode
Version: 0.11.7
Summary: django-maintenancemode allows you to temporary shutdown your site for maintenance work
Home-page: https://github.com/shanx/django-maintenancemode
Author: Remco Wendt
Author-email: remco@maykinmedia.nl
Maintainer: Basil Shubin
Maintainer-email: basil.shubin@gmail.com
License: BSD License
Download-URL: https://github.com/shanx/django-maintenancemode/zipball/master
Platform: UNKNOWN
Classifier: Development Status :: 5 - Production/Stable
Classifier: Environment :: Web Environment
Classifier: Intended Audience :: Developers
Classifier: License :: OSI Approved :: BSD License
Classifier: Operating System :: OS Independent
Classifier: Programming Language :: Python
Classifier: Programming Language :: Python :: 3 :: Only
Classifier: Programming Language :: Python :: 3.6
Classifier: Programming Language :: Python :: 3.7
Classifier: Programming Language :: Python :: 3.8
Classifier: Programming Language :: Python :: 3.9
Classifier: Framework :: Django
Classifier: Framework :: Django :: 2.2
Classifier: Framework :: Django :: 3.0
Classifier: Framework :: Django :: 3.1
Classifier: Framework :: Django :: 3.2
License-File: LICENSE
License-File: AUTHORS
Requires-Dist: django-appconf
Requires-Dist: six (>=1.9.0)
Requires-Dist: ipy
Provides-Extra: develop
Requires-Dist: tox ; extra == 'develop'
Requires-Dist: django ; extra == 'develop'
Requires-Dist: pytest-django ; extra == 'develop'
Requires-Dist: pytest ; extra == 'develop'
Provides-Extra: test
Requires-Dist: pytest-django ; extra == 'test'
Requires-Dist: pytest-cov ; extra == 'test'
Requires-Dist: pytest ; extra == 'test'
